engagelab/__init__.py
Engagelab_Python_SDK-0.0.1.dist-info/METADATA
Engagelab_Python_SDK-0.0.1.dist-info/WHEEL
Engagelab_Python_SDK-0.0.1.dist-info/top_level.txt
Engagelab_Python_SDK-0.0.1.dist-info/RECORD
