Metadata-Version: 2.1
Name: Engagelab-Python-SDK
Version: 0.0.1
Summary: World-leading Customer Engagement Platform
Home-page: https://docs.engagelab.com
Author: catroll
Author-email: 
License: UNKNOWN
Keywords: Email
Platform: UNKNOWN
Requires-Dist: urllib3 (>=1.15)
Requires-Dist: six (>=1.10)
Requires-Dist: certifi
Requires-Dist: python-dateutil
